{
    "_links": {
        "self": {
            "href": "http:\/\/default\/taxonomy\/term\/20?_format=hal_json"
        },
        "type": {
            "href": "http:\/\/drupal.org\/rest\/type\/taxonomy_term\/district"
        }
    },
    "tid": [
        {
            "value": 20
        }
    ],
    "uuid": [
        {
            "value": "cbd83438-831a-433a-95cd-c3f55c61698d"
        }
    ],
    "langcode": [
        {
            "value": "es",
            "lang": "es"
        }
    ],
    "vid": [
        {
            "target_id": "district"
        }
    ],
    "name": [
        {
            "value": "District B",
            "lang": "es"
        }
    ],
    "weight": [
        {
            "value": 1
        }
    ],
    "changed": [
        {
            "value": "2017-12-15T18:36:05+00:00",
            "lang": "es",
            "format": "Y-m-d\\TH:i:sP"
        }
    ],
    "default_langcode": [
        {
            "value": true,
            "lang": "es"
        }
    ]
}